odc/apps/cloud/__init__.py
odc/apps/cloud/_version.py
odc/apps/cloud/azure_to_tar.py
odc/apps/cloud/gs_to_tar.py
odc/apps/cloud/redrive_to_queue.py
odc/apps/cloud/s3_find.py
odc/apps/cloud/s3_inventory.py
odc/apps/cloud/s3_to_tar.py
odc/apps/cloud/thredds_to_tar.py
odc_apps_cloud-0.2.3.dist-info/LICENSE
odc_apps_cloud-0.2.3.dist-info/METADATA
odc_apps_cloud-0.2.3.dist-info/WHEEL
odc_apps_cloud-0.2.3.dist-info/entry_points.txt
odc_apps_cloud-0.2.3.dist-info/top_level.txt
odc_apps_cloud-0.2.3.dist-info/RECORD
